odoo/addons/agreement_rebate_partner_company_group/README.rst
odoo/addons/agreement_rebate_partner_company_group/__init__.py
odoo/addons/agreement_rebate_partner_company_group/__manifest__.py
odoo/addons/agreement_rebate_partner_company_group/i18n/agreement_rebate_partner_company_group.pot
odoo/addons/agreement_rebate_partner_company_group/readme/CONTRIBUTORS.rst
odoo/addons/agreement_rebate_partner_company_group/readme/DESCRIPTION.rst
odoo/addons/agreement_rebate_partner_company_group/readme/USAGE.rst
odoo/addons/agreement_rebate_partner_company_group/static/description/icon.png
odoo/addons/agreement_rebate_partner_company_group/static/description/index.html
odoo/addons/agreement_rebate_partner_company_group/tests/__init__.py
odoo/addons/agreement_rebate_partner_company_group/tests/test_agreement_rebate.py
odoo/addons/agreement_rebate_partner_company_group/wizards/__init__.py
odoo/addons/agreement_rebate_partner_company_group/wizards/settlement_create.py
odoo13_addon_agreement_rebate_partner_company_group-13.0.1.0.1.dev3.dist-info/METADATA
odoo13_addon_agreement_rebate_partner_company_group-13.0.1.0.1.dev3.dist-info/WHEEL
odoo13_addon_agreement_rebate_partner_company_group-13.0.1.0.1.dev3.dist-info/top_level.txt
odoo13_addon_agreement_rebate_partner_company_group-13.0.1.0.1.dev3.dist-info/RECORD
